aioworkers_mongo/__init__.py
aioworkers_mongo/base.py
aioworkers_mongo-0.2.1.dist-info/LICENSE
aioworkers_mongo-0.2.1.dist-info/WHEEL
aioworkers_mongo-0.2.1.dist-info/METADATA
aioworkers_mongo-0.2.1.dist-info/RECORD
