Metadata-Version: 2.1
Name: aioworkers-mongo
Version: 0.2.1
Summary: Module for working with MongoDB via asyncpg
Home-page: https://github.com/aioworkers/aioworkers-mongo
License: Apache Software License 2.0
Author: Alexander Bogushov
Author-email: abogushov@gmail.com
Requires-Python: >=3.6,<3.11
Classifier: Development Status :: 2 - Pre-Alpha
Classifier: Intended Audience :: Developers
Classifier: License :: OSI Approved :: Apache Software License
Classifier: License :: Other/Proprietary License
Classifier: Programming Language :: Python :: 3
Classifier: Programming Language :: Python :: 3.10
Classifier: Programming Language :: Python :: 3.6
Classifier: Programming Language :: Python :: 3.7
Classifier: Programming Language :: Python :: 3.8
Classifier: Programming Language :: Python :: 3.9
Requires-Dist: aioworkers (>=0.13)
Requires-Dist: motor (>=1.3,<2.0)
Project-URL: Repository, https://github.com/aioworkers/aioworkers-mongo
